SimPy/GUIDebug.py
SimPy/Globals.py
SimPy/Lib.py
SimPy/Lister.py
SimPy/Recording.py
SimPy/SimGUI.py
SimPy/SimPlot.py
SimPy/Simulation.py
SimPy/SimulationGUIDebug.py
SimPy/SimulationRT.py
SimPy/SimulationStep.py
SimPy/SimulationTrace.py
SimPy/__init__.py
SimPy/canvas.py
SimPy/stepping.py
SimPy/tkconsole.py
SimPy/tkprogressbar.py
SimPy/test/__init__.py
SimPy/test/test_monitor.py
SimPy/test/test_rt_behavior.py
SimPy/test/test_simident.py
SimPy/test/test_simpy.py
SimPyClassic-2.3.4.dist-info/DESCRIPTION.rst
SimPyClassic-2.3.4.dist-info/LICENSE.txt
SimPyClassic-2.3.4.dist-info/METADATA
SimPyClassic-2.3.4.dist-info/RECORD
SimPyClassic-2.3.4.dist-info/WHEEL
SimPyClassic-2.3.4.dist-info/metadata.json
SimPyClassic-2.3.4.dist-info/top_level.txt
