Metadata-Version: 2.0
Name: SimPyClassic
Version: 2.3.4
Summary: Event discrete, process based simulation for Python.
Home-page: https://github.com/SimPyClassic/SimPyClassic
Author: Klaus Muller, Tony Vignaux, Ontje Lünsdorf, Stefan Scherfke
Author-email: UNKNOWN
License: GNU LGPL
Download-URL: https://github.com/SimPyClassic/SimPyClassic/releases
Platform: UNKNOWN
Classifier: Programming Language :: Python
Classifier: Programming Language :: Python :: 2.7
Classifier: Programming Language :: Python :: 3
Classifier: Programming Language :: Python :: 3.4
Classifier: Programming Language :: Python :: 3.5
Classifier: Programming Language :: Python :: 3.6
Classifier: Programming Language :: Python :: Implementation :: PyPy
Classifier: Operating System :: OS Independent
Classifier: License :: OSI Approved :: GNU Library or Lesser General Public License (LGPL)
Classifier: Development Status :: 5 - Production/Stable
Classifier: Intended Audience :: Science/Research
Classifier: Topic :: Scientific/Engineering
